mygfa/__init__.py
mygfa/__main__.py
mygfa/gfa.py
mygfa/preprocess.py
mygfa-0.1.dist-info/WHEEL
mygfa-0.1.dist-info/METADATA
mygfa-0.1.dist-info/RECORD
