Metadata-Version: 2.1
Name: mygfa
Version: 0.1
Summary: Simple GFA parsing, printing, and pre-processing in Python.
Author-email: Anshuman Mohan <amohan@cs.cornell.edu>
Classifier: License :: OSI Approved :: MIT License
Project-URL: Home, https://github.com/cucapra/pollen/tree/main/mygfa
